{
  "Book": [
    {
      "BookName": "Philemon",
      "Chapter": [
        {
          "Chapterid": "1",
          "Verse": [
            {
              "Verseid": "00000001",
              "Verse": "Paul, a prisoner of Christ Jesus, and Timothy our brother, To Philemon our dear friend and fellow worker—"
            },
            {
              "Verseid": "00000002",
              "Verse": "also to Apphia our sister and Archippus our fellow soldier—and to the church that meets in your home:"
            },
            {
              "Verseid": "00000003",
              "Verse": "Grace and peace to you from God our Father and the Lord Jesus Christ."
            },
            {
              "Verseid": "00000004",
              "Verse": "I always thank my God as I remember you in my prayers,"
            },
            {
              "Verseid": "00000005",
              "Verse": "because I hear about your love for all his holy people and your faith in the Lord Jesus."
            },
            {
              "Verseid": "00000006",
              "Verse": "I pray that your partnership with us in the faith may be effective in deepening your understanding of every good thing we share for the sake of Christ."
            },
            {
              "Verseid": "00000007",
              "Verse": "Your love has given me great joy and encouragement, because you, brother, have refreshed the hearts of the Lord`s people."
            },
            {
              "Verseid": "00000008",
              "Verse": "Therefore, although in Christ I could be bold and order you to do what you ought to do,"
            },
            {
              "Verseid": "00000009",
              "Verse": "yet I prefer to appeal to you on the basis of love. It is as none other than Paul—an old man and now also a prisoner of Christ Jesus—"
            },
            {
              "Verseid": "00000010",
              "Verse": "that I appeal to you for my son Onesimus, who became my son while I was in chains."
            },
            {
              "Verseid": "00000011",
              "Verse": "Formerly he was useless to you, but now he has become useful both to you and to me."
            },
            {
              "Verseid": "00000012",
              "Verse": "I am sending him—who is my very heart—back to you."
            },
            {
              "Verseid": "00000013",
              "Verse": "I would have liked to keep him with me so that he could take your place in helping me while I am in chains for the gospel."
            },
            {
              "Verseid": "00000014",
              "Verse": "But I did not want to do anything without your consent, so that any favor you do would not seem forced but would be voluntary."
            },
            {
              "Verseid": "00000015",
              "Verse": "Perhaps the reason he was separated from you for a little while was that you might have him back forever—"
            },
            {
              "Verseid": "00000016",
              "Verse": "no longer as a slave, but better than a slave, as a dear brother. He is very dear to me but even dearer to you, both as a fellow man and as a brother in the Lord."
            },
            {
              "Verseid": "00000017",
              "Verse": "So if you consider me a partner, welcome him as you would welcome me."
            },
            {
              "Verseid": "00000018",
              "Verse": "If he has done you any wrong or owes you anything, charge it to me."
            },
            {
              "Verseid": "00000019",
              "Verse": "I, Paul, am writing this with my own hand. I will pay it back—not to mention that you owe me your very self."
            },
            {
              "Verseid": "00000020",
              "Verse": "I do wish, brother, that I may have some benefit from you in the Lord; refresh my heart in Christ."
            },
            {
              "Verseid": "00000021",
              "Verse": "Confident of your obedience, I write to you, knowing that you will do even more than I ask."
            },
            {
              "Verseid": "00000022",
              "Verse": "And one thing more: Prepare a guest room for me, because I hope to be restored to you in answer to your prayers."
            },
            {
              "Verseid": "00000023",
              "Verse": "Epaphras, my fellow prisoner in Christ Jesus, sends you greetings."
            },
            {
              "Verseid": "00000024",
              "Verse": "And so do Mark, Aristarchus, Demas and Luke, my fellow workers."
            },
            {
              "Verseid": "00000025",
              "Verse": "The grace of the Lord Jesus Christ be with your spirit."
            }
          ]
        }
      ]
    }
  ]
}